eamin/__init__.py
eamin-0.1.0.dist-info/LICENSE
eamin-0.1.0.dist-info/METADATA
eamin-0.1.0.dist-info/WHEEL
eamin-0.1.0.dist-info/top_level.txt
eamin-0.1.0.dist-info/RECORD
